libmonty_artnet/__init__.py
libmonty_artnet/__main__.py
libmonty_artnet/version.py
libmonty_artnet/config/__init__.py
libmonty_artnet/config/app.py
libmonty_artnet/controller/__init__.py
libmonty_artnet/controller/controller.py
libmonty_artnet/data/oem-codes.csv
libmonty_artnet/packets/__init__.py
libmonty_artnet/packets/art_address.py
libmonty_artnet/packets/art_command.py
libmonty_artnet/packets/art_diag_data.py
libmonty_artnet/packets/art_dmx.py
libmonty_artnet/packets/art_input.py
libmonty_artnet/packets/art_ip_prog.py
libmonty_artnet/packets/art_ip_prog_reply.py
libmonty_artnet/packets/art_nzs.py
libmonty_artnet/packets/art_poll.py
libmonty_artnet/packets/art_poll_reply.py
libmonty_artnet/packets/art_sync.py
libmonty_artnet/packets/art_time_code.py
libmonty_artnet/packets/art_trigger.py
libmonty_artnet/packets/art_vlc.py
libmonty_artnet/packets/base.py
libmonty_artnet/protocol/__init__.py
libmonty_artnet/protocol/constants.py
libmonty_artnet/protocol/diag_priority_codes.py
libmonty_artnet/protocol/op_codes.py
libmonty_artnet/utils/__init__.py
libmonty_artnet/utils/common_args.py
libmonty_artnet/utils/grid.py
libmonty_artnet/utils/network.py
libmonty_artnet-0.2.0.dist-info/LICENSE
libmonty_artnet-0.2.0.dist-info/METADATA
libmonty_artnet-0.2.0.dist-info/WHEEL
libmonty_artnet-0.2.0.dist-info/entry_points.txt
libmonty_artnet-0.2.0.dist-info/top_level.txt
libmonty_artnet-0.2.0.dist-info/RECORD
