Metadata-Version: 2.1
Name: libmonty-artnet
Version: 0.2.0
Summary: libmonty-artnet - Art-Net™ protocol implementation
Home-page: https://codeberg.org/sunarch/libmonty-artnet
Author: András Németh (sunarch)
Author-email: sunarch@protonmail.com
Maintainer: András Németh (sunarch)
Maintainer-email: sunarch@protonmail.com
License: Mozilla Public License 2.0 (MPL 2.0)
Project-URL: Bug Tracker, https://codeberg.org/sunarch/libmonty-artnet/issues
Keywords: libmonty,libmonty-artnet,Art-Net,Artistic Licence
Platform: Any
Classifier: Programming Language :: Python :: 3
Classifier: License :: OSI Approved :: Mozilla Public License 2.0 (MPL 2.0)
Classifier: Operating System :: OS Independent
Classifier: Environment :: Console
Classifier: Environment :: Web Environment
Classifier: Development Status :: 2 - Pre-Alpha
Classifier: Intended Audience :: End Users/Desktop
Classifier: Intended Audience :: Developers
Classifier: Topic :: Artistic Software
Classifier: Topic :: Multimedia
Classifier: Topic :: System :: Networking
Classifier: Typing :: Typed
Requires-Python: >=3.9
License-File: LICENSE
Requires-Dist: libmonty-logging (==0.1.1)
Requires-Dist: webcolors (~=1.12)
